my_math/__init__.py
my_math/calculate.py
my_maths-0.0.1.dist-info/METADATA
my_maths-0.0.1.dist-info/WHEEL
my_maths-0.0.1.dist-info/top_level.txt
my_maths-0.0.1.dist-info/RECORD
